projet_gcb202a23/__init__.py
projet_gcb202a23-1.1.0.dist-info/METADATA
projet_gcb202a23-1.1.0.dist-info/WHEEL
projet_gcb202a23-1.1.0.dist-info/top_level.txt
projet_gcb202a23-1.1.0.dist-info/RECORD
