Metadata-Version: 2.1
Name: projet_gcb202a23
Version: 1.1.0
Summary: Projet GCB202A23
Home-page: https://catalyseur.ca
Author: Francis B. Lavoie
Author-email: francis.b.lavoie@usherbrooke.ca
Classifier: Programming Language :: Python :: 3
Classifier: License :: OSI Approved :: MIT License
Classifier: Operating System :: OS Independent
